attachments/__init__.py
attachments/admin.py
attachments/apps.py
attachments/exceptions.py
attachments/forms.py
attachments/models.py
attachments/signals.py
attachments/urls.py
attachments/utils.py
attachments/views.py
attachments/migrations/0001_initial.py
attachments/migrations/0002_property.py
attachments/migrations/0003_auto_20150317_1319.py
attachments/migrations/0004_auto_20150507_1438.py
attachments/migrations/0005_auto_20150708_1435.py
attachments/migrations/0006_session_content_type.py
attachments/migrations/0007_property_required.py
attachments/migrations/0008_session_data.py
attachments/migrations/0009_auto_20170202_1700.py
attachments/migrations/0010_property_is_editable.py
attachments/migrations/0011_session_allowed_file_types.py
attachments/migrations/0012_auto_20180906_1449.py
attachments/migrations/0013_auto_20191107_1122.py
attachments/migrations/0014_auto_20220615_1524.py
attachments/migrations/0015_session_unpack_zip_files.py
attachments/migrations/0016_alter_attachment_id_alter_property_id_and_more.py
attachments/migrations/__init__.py
attachments/static/attachments/css/attachments.css
attachments/static/attachments/js/attachments.js
attachments/static/attachments/js/jquery.iframe-transport.js
attachments/templates/attachments/edit_properties.html
attachments/templates/attachments/form.html
attachments/templates/attachments/list.html
attachments/templates/attachments/view_properties.html
attachments/templates/attachments/bootstrap/form.html
attachments/templates/attachments/bootstrap/list.html
attachments/templates/attachments/bootstrap/view_properties.html
attachments/templatetags/__init__.py
attachments/templatetags/attachments.py
django_dynamic_attachments-5.0.0.dist-info/METADATA
django_dynamic_attachments-5.0.0.dist-info/WHEEL
django_dynamic_attachments-5.0.0.dist-info/licenses/LICENSE
django_dynamic_attachments-5.0.0.dist-info/RECORD
